ssh_ipykernel/__init__.py
ssh_ipykernel/__main__.py
ssh_ipykernel/_version.py
ssh_ipykernel/kernel.py
ssh_ipykernel/manage.py
ssh_ipykernel/status.py
ssh_ipykernel/utils.py
ssh_ipykernel/ssh_ipykernel_interrupt/__init__.py
ssh_ipykernel/ssh_ipykernel_interrupt/interrupt_handler.py
ssh_ipykernel/ssh_ipykernel_interrupt/jupyter_server/ssh-ipykernel-interrupt.json
ssh_ipykernel-1.2.3.data/data/etc/jupyter/jupyter_server_config.d/ssh-ipykernel-interrupt.json
ssh_ipykernel-1.2.3.dist-info/AUTHORS.md
ssh_ipykernel-1.2.3.dist-info/LICENSE
ssh_ipykernel-1.2.3.dist-info/METADATA
ssh_ipykernel-1.2.3.dist-info/WHEEL
ssh_ipykernel-1.2.3.dist-info/top_level.txt
ssh_ipykernel-1.2.3.dist-info/RECORD
