Metadata-Version: 2.1
Name: ssh-ipykernel
Version: 1.2.3
Summary: A remote jupyter ipykernel via ssh
Home-page: https://github.com/bernhard-42/ssh_ipykernel
Author: Bernhard Walter
Author-email: b_walter@arcor.de
License: MIT license
Keywords: ssh_ipykernel
Platform: UNKNOWN
Classifier: Development Status :: 4 - Beta
Classifier: Intended Audience :: Developers
Classifier: License :: OSI Approved :: MIT License
Classifier: Natural Language :: English
Classifier: Programming Language :: Python :: 3.5
Classifier: Programming Language :: Python :: 3.6
Classifier: Programming Language :: Python :: 3.7
Classifier: Programming Language :: Python :: 3.8
Requires-Python: >=3.5
Requires-Dist: tornado (<=6.2.0,>=6.1.0)
Requires-Dist: jupyter-client (<6.2.0,>=6.1.12)
Requires-Dist: jupyterlab (<3.1.0,>=3.0.0)
Requires-Dist: ssh-ipykernel-interrupt (==1.1.2)
Requires-Dist: pexpect (==4.8.0) ; platform_system != "Windows"
Requires-Dist: wexpect (==3.3.2) ; platform_system == "Windows"
Provides-Extra: dev
Requires-Dist: pylint ; extra == 'dev'
Requires-Dist: black ; extra == 'dev'
Requires-Dist: bumpversion ; extra == 'dev'
Requires-Dist: twine ; extra == 'dev'
Requires-Dist: wheel ; extra == 'dev'
